{
    "$schema": "https://developer.microsoft.com/json-schemas/fabric/item/report/definition/visualContainer/2.5.0/schema.json",
    "name": "e46e131aee60cb083718",
    "position": {
        "x": 9.546302050963332,
        "y": 883.6708860759493,
        "z": 1000,
        "height": 200,
        "width": 1900,
        "tabOrder": 14000
    },
    "visual": {
        "visualType": "columnChart",
        "query": {
            "queryState": {
                "Category": {
                    "projections": [
                        {
                            "field": {
                                "Column": {
                                    "Expression": {
                                        "SourceRef": {
                                            "Entity": "calendar"
                                        }
                                    },
                                    "Property": "Date2Key"
                                }
                            },
                            "queryRef": "calendar.Date2Key",
                            "nativeQueryRef": "Date2Key",
                            "active": true
                        }
                    ]
                },
                "Series": {
                    "projections": [
                        {
                            "field": {
                                "Column": {
                                    "Expression": {
                                        "SourceRef": {
                                            "Entity": "activities"
                                        }
                                    },
                                    "Property": "CapacityName"
                                }
                            },
                            "queryRef": "activities.CapacityName",
                            "nativeQueryRef": "CapacityName"
                        }
                    ]
                },
                "Y": {
                    "projections": [
                        {
                            "field": {
                                "Measure": {
                                    "Expression": {
                                        "SourceRef": {
                                            "Entity": "Metrics"
                                        }
                                    },
                                    "Property": "# Activities"
                                }
                            },
                            "queryRef": "Metrics.# Activities",
                            "nativeQueryRef": "# Activities1"
                        }
                    ]
                }
            },
            "sortDefinition": {
                "sort": [
                    {
                        "field": {
                            "Column": {
                                "Expression": {
                                    "SourceRef": {
                                        "Entity": "calendar"
                                    }
                                },
                                "Property": "Date2Key"
                            }
                        },
                        "direction": "Ascending"
                    }
                ]
            }
        },
        "objects": {
            "categoryAxis": [
                {
                    "properties": {
                        "axisType": {
                            "expr": {
                                "Literal": {
                                    "Value": "'Scalar'"
                                }
                            }
                        },
                        "gridlineColor": {
                            "solid": {
                                "color": {
                                    "expr": {
                                        "ThemeDataColor": {
                                            "ColorId": 0,
                                            "Percent": -0.5
                                        }
                                    }
                                }
                            }
                        },
                        "showAxisTitle": {
                            "expr": {
                                "Literal": {
                                    "Value": "false"
                                }
                            }
                        }
                    }
                }
            ],
            "labels": [
                {
                    "properties": {
                        "show": {
                            "expr": {
                                "Literal": {
                                    "Value": "false"
                                }
                            }
                        }
                    }
                }
            ],
            "legend": [
                {
                    "properties": {
                        "position": {
                            "expr": {
                                "Literal": {
                                    "Value": "'Right'"
                                }
                            }
                        },
                        "showGradientLegend": {
                            "expr": {
                                "Literal": {
                                    "Value": "false"
                                }
                            }
                        },
                        "show": {
                            "expr": {
                                "Literal": {
                                    "Value": "false"
                                }
                            }
                        }
                    }
                }
            ],
            "ribbonBands": [
                {
                    "properties": {
                        "show": {
                            "expr": {
                                "Literal": {
                                    "Value": "false"
                                }
                            }
                        },
                        "fillTransparency": {
                            "expr": {
                                "Literal": {
                                    "Value": "70D"
                                }
                            }
                        }
                    }
                }
            ],
            "totals": [
                {
                    "properties": {
                        "show": {
                            "expr": {
                                "Literal": {
                                    "Value": "true"
                                }
                            }
                        },
                        "labelDisplayUnits": {
                            "expr": {
                                "Literal": {
                                    "Value": "1D"
                                }
                            }
                        }
                    }
                }
            ],
            "valueAxis": [
                {
                    "properties": {
                        "gridlineColor": {
                            "solid": {
                                "color": {
                                    "expr": {
                                        "ThemeDataColor": {
                                            "ColorId": 0,
                                            "Percent": -0.5
                                        }
                                    }
                                }
                            }
                        }
                    }
                }
            ]
        },
        "visualContainerObjects": {
            "title": [
                {
                    "properties": {
                        "show": {
                            "expr": {
                                "Literal": {
                                    "Value": "true"
                                }
                            }
                        },
                        "text": {
                            "expr": {
                                "Literal": {
                                    "Value": "'Activities on Dedicated Capacities'"
                                }
                            }
                        },
                        "fontSize": {
                            "expr": {
                                "Literal": {
                                    "Value": "12D"
                                }
                            }
                        }
                    }
                }
            ],
            "border": [
                {
                    "properties": {
                        "show": {
                            "expr": {
                                "Literal": {
                                    "Value": "true"
                                }
                            }
                        },
                        "radius": {
                            "expr": {
                                "Literal": {
                                    "Value": "5D"
                                }
                            }
                        }
                    }
                }
            ],
            "dropShadow": [
                {
                    "properties": {
                        "show": {
                            "expr": {
                                "Literal": {
                                    "Value": "true"
                                }
                            }
                        },
                        "color": {
                            "solid": {
                                "color": {
                                    "expr": {
                                        "ThemeDataColor": {
                                            "ColorId": 0,
                                            "Percent": -0.1
                                        }
                                    }
                                }
                            }
                        }
                    }
                }
            ],
            "visualTooltip": [
                {
                    "properties": {
                        "type": {
                            "expr": {
                                "Literal": {
                                    "Value": "'Default'"
                                }
                            }
                        }
                    }
                }
            ]
        },
        "drillFilterOtherVisuals": true
    },
    "filterConfig": {
        "filters": [
            {
                "name": "Filtera9c1fb716a35e193dc11",
                "ordinal": 0,
                "field": {
                    "Column": {
                        "Expression": {
                            "SourceRef": {
                                "Entity": "activities"
                            }
                        },
                        "Property": "CapacityId"
                    }
                },
                "type": "Categorical",
                "filter": {
                    "Version": 2,
                    "From": [
                        {
                            "Name": "a",
                            "Entity": "activities",
                            "Type": 0
                        }
                    ],
                    "Where": [
                        {
                            "Condition": {
                                "Not": {
                                    "Expression": {
                                        "In": {
                                            "Expressions": [
                                                {
                                                    "Column": {
                                                        "Expression": {
                                                            "SourceRef": {
                                                                "Source": "a"
                                                            }
                                                        },
                                                        "Property": "CapacityId"
                                                    }
                                                }
                                            ],
                                            "Values": [
                                                [
                                                    {
                                                        "Literal": {
                                                            "Value": "null"
                                                        }
                                                    }
                                                ]
                                            ]
                                        }
                                    }
                                }
                            }
                        }
                    ]
                },
                "howCreated": "User",
                "objects": {
                    "general": [
                        {
                            "properties": {
                                "isInvertedSelectionMode": {
                                    "expr": {
                                        "Literal": {
                                            "Value": "true"
                                        }
                                    }
                                }
                            }
                        }
                    ]
                }
            },
            {
                "name": "840a999a417aa0036a02",
                "ordinal": 1,
                "field": {
                    "Column": {
                        "Expression": {
                            "SourceRef": {
                                "Entity": "calendar"
                            }
                        },
                        "Property": "Date2Key"
                    }
                },
                "type": "Categorical"
            },
            {
                "name": "7f86fdd37a00b65da41e",
                "ordinal": 2,
                "field": {
                    "Measure": {
                        "Expression": {
                            "SourceRef": {
                                "Entity": "Metrics"
                            }
                        },
                        "Property": "# Activities"
                    }
                },
                "type": "Advanced"
            },
            {
                "name": "ed6fdbf36ad0aac29d2c",
                "ordinal": 3,
                "field": {
                    "Column": {
                        "Expression": {
                            "SourceRef": {
                                "Entity": "activities"
                            }
                        },
                        "Property": "CapacityName"
                    }
                },
                "type": "Categorical"
            },
            {
                "name": "724c39d8da845dde0892",
                "ordinal": 4,
                "field": {
                    "Column": {
                        "Expression": {
                            "SourceRef": {
                                "Entity": "calendar"
                            }
                        },
                        "Property": "YearMonth"
                    }
                },
                "type": "Categorical",
                "howCreated": "User"
            }
        ],
        "filterSortOrder": "Custom"
    }
}