{
    "$schema": "https://developer.microsoft.com/json-schemas/fabric/item/report/definition/visualContainer/2.5.0/schema.json",
    "name": "947733ab60d83d0a68e4",
    "position": {
        "x": 587.0646726328465,
        "y": 185.24590163934425,
        "z": 14000,
        "height": 80.32786885245902,
        "width": 191.80327868852459,
        "tabOrder": 13000
    },
    "visual": {
        "visualType": "tableEx",
        "query": {
            "queryState": {
                "Values": {
                    "projections": [
                        {
                            "field": {
                                "Measure": {
                                    "Expression": {
                                        "SourceRef": {
                                            "Entity": "Metrics"
                                        }
                                    },
                                    "Property": "Selected Capacity SKU"
                                }
                            },
                            "queryRef": "Metrics.Selected Capacity SKU",
                            "nativeQueryRef": "SKU based on last scan",
                            "displayName": "SKU based on last scan"
                        }
                    ]
                }
            }
        },
        "objects": {
            "general": [
                {
                    "properties": {}
                }
            ],
            "total": [
                {
                    "properties": {
                        "totals": {
                            "expr": {
                                "Literal": {
                                    "Value": "false"
                                }
                            }
                        }
                    }
                }
            ],
            "columnHeaders": [
                {
                    "properties": {
                        "fontSize": {
                            "expr": {
                                "Literal": {
                                    "Value": "10D"
                                }
                            }
                        },
                        "alignment": {
                            "expr": {
                                "Literal": {
                                    "Value": "'Center'"
                                }
                            }
                        },
                        "fontFamily": {
                            "expr": {
                                "Literal": {
                                    "Value": "'''Segoe UI'', wf_segoe-ui_normal, helvetica, arial, sans-serif'"
                                }
                            }
                        },
                        "fontColor": {
                            "solid": {
                                "color": {
                                    "expr": {
                                        "ThemeDataColor": {
                                            "ColorId": 2,
                                            "Percent": -0.25
                                        }
                                    }
                                }
                            }
                        }
                    }
                }
            ],
            "grid": [
                {
                    "properties": {
                        "outlineColor": {
                            "solid": {
                                "color": {
                                    "expr": {
                                        "ThemeDataColor": {
                                            "ColorId": 0,
                                            "Percent": -0.1
                                        }
                                    }
                                }
                            }
                        }
                    }
                }
            ],
            "values": [
                {
                    "properties": {
                        "fontSize": {
                            "expr": {
                                "Literal": {
                                    "Value": "13D"
                                }
                            }
                        },
                        "fontFamily": {
                            "expr": {
                                "Literal": {
                                    "Value": "'''Segoe UI Semibold'', wf_segoe-ui_semibold, helvetica, arial, sans-serif'"
                                }
                            }
                        }
                    }
                }
            ],
            "columnWidth": [
                {
                    "properties": {
                        "value": {
                            "expr": {
                                "Literal": {
                                    "Value": "168.7756956144555D"
                                }
                            }
                        }
                    },
                    "selector": {
                        "metadata": "Metrics.Selected Capacity SKU"
                    }
                }
            ],
            "columnFormatting": [
                {
                    "properties": {
                        "alignment": {
                            "expr": {
                                "Literal": {
                                    "Value": "'Center'"
                                }
                            }
                        }
                    },
                    "selector": {
                        "metadata": "Metrics.Selected Capacity SKU"
                    }
                }
            ]
        },
        "visualContainerObjects": {
            "dropShadow": [
                {
                    "properties": {
                        "show": {
                            "expr": {
                                "Literal": {
                                    "Value": "true"
                                }
                            }
                        },
                        "color": {
                            "solid": {
                                "color": {
                                    "expr": {
                                        "ThemeDataColor": {
                                            "ColorId": 0,
                                            "Percent": -0.2
                                        }
                                    }
                                }
                            }
                        }
                    }
                }
            ],
            "border": [
                {
                    "properties": {
                        "radius": {
                            "expr": {
                                "Literal": {
                                    "Value": "8D"
                                }
                            }
                        }
                    }
                }
            ]
        },
        "drillFilterOtherVisuals": true
    },
    "filterConfig": {
        "filters": [
            {
                "name": "ecca6a8a1461bce948dc",
                "field": {
                    "Measure": {
                        "Expression": {
                            "SourceRef": {
                                "Entity": "Metrics"
                            }
                        },
                        "Property": "Selected Capacity SKU"
                    }
                },
                "type": "Advanced"
            }
        ]
    }
}